pumper/__init__.py
pumper/command.py
pumper/logging.py
pumper/main.py
pumper/tools.py
pumper-0.2.0.dist-info/METADATA
pumper-0.2.0.dist-info/WHEEL
pumper-0.2.0.dist-info/entry_points.txt
pumper-0.2.0.dist-info/licenses/LICENSE.txt
pumper-0.2.0.dist-info/RECORD
