Metadata-Version: 2.1
Name: pumper
Version: 0.2.0
Summary: Automatically create a PR, bump version (using Commitizen), approve and merge (suitable for CI/CD).
Project-URL: Documentation, https://github.com/aka-raccoon/pumper#readme
Project-URL: Issues, https://github.com/aka-raccoon/pumper/issues
Project-URL: Source, https://github.com/aka-raccoon/pumper
Author-email: aka-raccoon <aka-raccoon@pm.me>
License: MIT License
License-File: LICENSE.txt
Keywords: bump,ci/cd,commitizen,gh actions
Classifier: Programming Language :: Python
Classifier: Programming Language :: Python :: 3.9
Classifier: Programming Language :: Python :: 3.10
Classifier: Programming Language :: Python :: 3.11
Classifier: Programming Language :: Python :: Implementation :: CPython
Classifier: Programming Language :: Python :: Implementation :: PyPy
Requires-Python: >=3.9
Requires-Dist: commitizen<=2.42.0
Requires-Dist: pygithub<=1.57
Requires-Dist: typer[all]<=0.7.0
Provides-Extra: dev
Requires-Dist: bandit[toml]; extra == 'dev'
Requires-Dist: black; extra == 'dev'
Requires-Dist: isort; extra == 'dev'
Requires-Dist: mypy; extra == 'dev'
Requires-Dist: pylint; extra == 'dev'
Provides-Extra: test
Requires-Dist: coverage; extra == 'test'
Requires-Dist: pytest; extra == 'test'
Requires-Dist: pytest-cov; extra == 'test'
Requires-Dist: pytest-mock; extra == 'test'
